shadybackend/__init__.py
shadybackend/api.py
shadybackend/api_tools.py
shadybackend/bridges.py
shadybackend/demon.py
shadybackend/discord_bridge.py
shadybackend/keys
shadybackend/log.py
shadybackend/request_tools.py
shadybackend/top_level.py
shadybackend/top_level.py.92d64f83b890fc49bbb92963ccee127d.py
shadybackend-0.1.0.dist-info/METADATA
shadybackend-0.1.0.dist-info/WHEEL
shadybackend-0.1.0.dist-info/entry_points.txt
shadybackend-0.1.0.dist-info/RECORD
