Metadata-Version: 2.1
Name: shadybackend
Version: 0.1.0
Summary: The defualt tool-chain for the SHADY Stack.
Author: USER 1103
Author-email: 79700949+user-1103@users.noreply.github.com
Requires-Python: >=3.10,<4.0
Classifier: Programming Language :: Python :: 3
Classifier: Programming Language :: Python :: 3.10
Classifier: Programming Language :: Python :: 3.11
Requires-Dist: Jinja2 (>=3.1.2,<4.0.0)
Requires-Dist: discord.py (>=2.2.0,<3.0.0)
